LICENSE
MANIFEST.in
README.rst
requirements.txt
setup.cfg
setup.py
charpy/Cruncher.py
charpy/__init__.py
charpy/cruncher.py
charpy/utils.py
charpy.egg-info/PKG-INFO
charpy.egg-info/SOURCES.txt
charpy.egg-info/dependency_links.txt
charpy.egg-info/not-zip-safe
charpy.egg-info/requires.txt
charpy.egg-info/top_level.txt
charpy/chartjs/__init__.py
charpy/chartjs/chart.py
charpy/chartjs/color.py
charpy/flask/__init__.py
charpy/flask/app.py
charpy/flask/factory.py
charpy/flask/blueprints/__init__.py
charpy/flask/blueprints/chart_demo.py
charpy/flask/blueprints/chartjs_api.py
charpy/flask/blueprints/dataframe_api.py
charpy/flask/blueprints/default.py
tests/__init__.py
tests/test_app_factory.py
tests/test_chart.py
tests/test_chart_color.py
tests/test_orc.py
tests/test_utils.py