Metadata-Version: 2.1
Name: charpy
Version: 0.8.1
Summary: Render chart from data
Home-page: http://github.com/sylhare/charpy
Author: sylhare
Author-email: sylhare@outlook.com
License: MIT
Keywords: flask chart.js web app chart charpy
Platform: UNKNOWN
Classifier: Development Status :: 3 - Alpha
Classifier: License :: OSI Approved :: MIT License
Classifier: Programming Language :: Python :: 3.6
Provides-Extra: dev
Provides-Extra: test
